ansible_cdk/__init__.py
ansible_cdk/__main__.py
ansible_cdk/_version.py
ansible_cdk/arg_parser.py
ansible_cdk/cli.py
ansible_cdk/version_builder.py
ansible_cdk-1.0.0.dist-info/LICENSE
ansible_cdk-1.0.0.dist-info/METADATA
ansible_cdk-1.0.0.dist-info/WHEEL
ansible_cdk-1.0.0.dist-info/entry_points.txt
ansible_cdk-1.0.0.dist-info/top_level.txt
ansible_cdk-1.0.0.dist-info/RECORD
